MANIFEST.in
README.txt
setup.cfg
setup.py
adi/__init__.py
adi.samplecontent.egg-info/PKG-INFO
adi.samplecontent.egg-info/SOURCES.txt
adi.samplecontent.egg-info/dependency_links.txt
adi.samplecontent.egg-info/entry_points.txt
adi.samplecontent.egg-info/namespace_packages.txt
adi.samplecontent.egg-info/not-zip-safe
adi.samplecontent.egg-info/paster_plugins.txt
adi.samplecontent.egg-info/requires.txt
adi.samplecontent.egg-info/top_level.txt
adi/samplecontent/__init__.py
adi/samplecontent/configure.zcml
adi/samplecontent/setuphandlers.py
adi/samplecontent/tests.py
adi/samplecontent/profiles/default/adi.samplecontent.marker.txt
adi/samplecontent/profiles/default/metadata.xml
adi/samplecontent/profiles/default/portlets.xml
docs/HISTORY.txt
docs/INSTALL.txt
docs/LICENSE.GPL
docs/LICENSE.txt