Metadata-Version: 1.0
Name: adi.samplecontent
Version: 0.2
Summary: Deletes Plone's default content and adds some sample content
Home-page: http://svn.plone.org/svn/collective/
Author: Ida Ebkes
Author-email: contact@ida-ebkes.eu
License: GPL
Platform: UNKNOWN
Classifier: Framework :: Plone
Classifier: Programming Language :: Python
